test/__init__.py
test/test_article_for_response.py
test/test_nlp_keywords_item_for_response.py
test/test_nlp_word_cut_item_for_response.py
test/test_url2_article_api.py
test/test_url2_nlp_api.py
url2io_client/__init__.py
url2io_client/api_client.py
url2io_client/configuration.py
url2io_client/rest.py
url2io_client/api/__init__.py
url2io_client/api/url2_article_api.py
url2io_client/api/url2_nlp_api.py
url2io_client/models/__init__.py
url2io_client/models/article_for_response.py
url2io_client/models/nlp_keywords_item_for_response.py
url2io_client/models/nlp_word_cut_item_for_response.py
url2io_client-1.0.1.dist-info/LICENSE
url2io_client-1.0.1.dist-info/METADATA
url2io_client-1.0.1.dist-info/WHEEL
url2io_client-1.0.1.dist-info/top_level.txt
url2io_client-1.0.1.dist-info/RECORD
