Metadata-Version: 2.1
Name: url2io-client
Version: 1.0.1
Summary: URL2io API SDK
Home-page: https://github.com/url2io/url2io-python-client
Author-email: url2@sina.com
License: MIT
Keywords: Swagger,URL2io API
Platform: UNKNOWN
Requires-Dist: certifi (>=2017.4.17)
Requires-Dist: python-dateutil (>=2.1)
Requires-Dist: six (>=1.10)
Requires-Dist: urllib3 (>=1.23)
